Metadata-Version: 2.1
Name: protobuf-wheel-builder
Version: 1.2.2
Summary: Python library for building protobuf wheels
Home-page: https://github.com/bdraco/protobuf-wheel-builder
Author: J. Nick Koston
Author-email: nick@koston.org
License: Apache Software License 2.0
Keywords: protobuf protobuf-wheel-builder
Classifier: Development Status :: 2 - Pre-Alpha
Classifier: Intended Audience :: Developers
Classifier: License :: OSI Approved :: Apache Software License
Classifier: Natural Language :: English
Classifier: Programming Language :: Python :: 3
Classifier: Programming Language :: Python :: 3.8
Classifier: Programming Language :: Python :: 3.9
Classifier: Programming Language :: Python :: 3.10
Requires-Python: >=3.8
License-File: LICENSE
